{"text": "[공연 공지]\\n<이음: 연결의 순간>\\n\\n우리는 같은 순간, 같은 감정을 나눌 때\\n비록 눈에 보이지 않아도 분명히 이어진 연결을 느낍니다.\\n\\n서로를 향한 실을 천천히 당기며 조금씩 가까워지고,\\n말 한마디 없이도 전해지는 온기를 알아차립니다.\\n\\n같은 온도와 같은 음악 속에서\\n서로의 눈을 바라보며 이어지는 그 순간들을 함께 모아봅니다.\\n\\n-\\nwith\\n정새벽 @noowad__\\n김결 @1_want_a.dimple\\n\\n[공연 정보]\\n일시 : 2025.08.30 (토) 오후 7시\\n장소 : 홍대 언플러그드 B1 공연장\\n티켓 : 사전 44,000원 / 현장 50,000원 (60석)\\n티켓오픈 : 2025.08.13 (수) 오후 7시\\n(@ourhome_zip 프로필링크 참조)\\n+ 예매오픈 일시 이전 제출된 예매내역은 무효처리됩니다.\\n+ 자세한 안내사항은 예매폼을 확인해주세요.\\n\\n문의 : @ourhome_zip DM", "TITLE": ["연결의 순간"], "DATE": ["2025.08.30", "2025.08.13", "2025년 8월 30일 (토)", "2025년 8월 13일 (수)"], "TIME": ["오후 7시"], "PRICE": ["44,000원", "50,000원"], "PRICE_ONSITE": ["50,000원"], "PRICE_TYPE": ["사전", "현매"], "LINEUP": ["정새벽", "김결", "모아봅니다"], "INSTAGRAM": ["@noowad__", "@1_want_a.dimple", "\\"], "VENUE": ["홍대"], "V_INSTA": [], "TICKET_OPEN_DATE": ["2025년 8월 13일 (수)"], "TICKET_OPEN_TIME": ["오후 7시"]}
{"text": "엔분의일 one over n LIVE 📅 2025.09.20 (SAT) 20:00 📍 우주파 (UZUPA, Jeju) 📍 해당 공연 예약 오픈 시간 2025.08.14 17:00 @one_over_n @uzupa_theuniversewave poster by @catchthespring ”우리 젊음을 나눠 먹자, 엔분의일로. Share our youth, OVRN“ 엔분의일의 음악 속에는 다섯 명의 목소리가 담겨 있다. 각자의 방식으로 해석한 이야기들이 모여, 하나의 곡이 완성된다. 그들이 노래하는 것은 나의 일상일 수도, 너의 고민일 수도, 우리 모두의 청춘일 수도 있다. 떠나버린 사랑이 남긴 슬픔, 열정이 바닥나 지쳐버린 나의 모습,한 평 남짓한 방에서 느껴지는 현실의 무게까지—그들의 노래 속에 녹아 있다. 엔분의일이 전하고 싶은 것은 거창한 위로가 아니다. 그저, 목소리가 관객에게 닿았을 때 ”너와 내가 그리 다르지 않다“는 공감이 전해지길 바랄 뿐이다. 서울의 대학에서 만난 다섯 친구들이 만든 밴드 엔분의일 (1/N) 입니다. (베이스 김명수, 보컬 신성규, 드럼 소순우, 기타 김예현, 기타 최훈) 밴드의 철학이자 목표를 아우르는 ’우리 젊음을 나눠 먹자, 엔분의일로‘ 문장 아래 어제보다 나은 오늘을 위해 꿈과 열정을 품고 살아가는 사람들과 함께 노래합니다. 느리지도 빠르지도 않게 우리만의 속도로 꾸준히 나아가고자 합니다. 🚀 1인 1음료 주문 필수! | 좌석 예약 추천! | 🎟 네이버에서 해당 아티스트 공연 예약 GO (선착순 X, 예약순 배치) 💡 공연 안내 -공연 10분 전까지 도착하지 않으면 예약 취소! -협소한 공간으로 인해 5인 이상 나누어 앉을 수 있음. -예약 없이 방문 시 스탠딩 또는 빈자리 착석 가능. -공연이 좋았다면 아티스트에게 팁을 보내주세요💙", "TITLE": ["엔분의일 one over n LIVE"], "DATE": ["2025.09.20", "2025.08.14", "2025년 9월 20일 (SAT)", "2025년 8월 14일"], "TIME": ["20:00", "17:00"], "PRICE": [], "PRICE_ONSITE": [], "PRICE_TYPE": [], "LINEUP": ["노래합니다", "문장 아래 어제보다 나은 오늘을 위해 꿈", "열정을 품고 살아가는 사람들"], "INSTAGRAM": ["@one_over_n", "@uzupa_theuniversewave", "@catchthespring"], "VENUE": ["우주파", "UZUPA"], "V_INSTA": [], "TICKET_OPEN_DATE": ["2025년 8월 14일"], "TICKET_OPEN_TIME": ["17:00"]}
{"text": "유기체 라이브 25.08.15. 금 20:00 박채령 @cher.rysii 이재규 @ejaegyu 임준형 @jjun_honey_ ⚪️유기체 라이브는 예매 없이 무료 입장 / 유료 퇴장으로 진행됩니다. 공간은 오후 3시부터 열려 있습니다. 유기체는 상식과 존중이 살아있는 건강한 예술 창작 환경을 바랍니다. 미성년자 출입 금지 외부 음료 및 주류 반입 불가", "TITLE": ["유기체 라이브"], "DATE": ["25.08", "25월 8일"], "TIME": ["20:00", "오후 3시"], "PRICE": ["무료"], "PRICE_ONSITE": [], "PRICE_TYPE": [], "LINEUP": ["박채령", "이재규", "임준형", "유기체"], "INSTAGRAM": ["@cher.rysii", "@ejaegyu", "@jjun_honey_"], "VENUE": [], "V_INSTA": [], "TICKET_OPEN_DATE": [], "TICKET_OPEN_TIME": []}
{"text": "[고요의 방 오픈마이크 #111] 1인 뮤지션을 대상으로 오픈마이크를 진행합니다. [ARTIST] 진화 @j__.lo.o2 서지영 @blu_salt 오윤 @woodangtang59 김명규 @l1them 공연일시 | 2025년 8월 16일 오후 3시 공연장소 | 서울 마포구 와우산로29길 14-10, 지층 입장시간 | 오후 2시 30분~ 티켓 | 현장판매 11,000원 문의 | @52dolz DM", "TITLE": ["방 오픈마이크 #111]"], "DATE": ["2025년 8월 16일"], "TIME": ["오후 3시", "오후 2시"], "PRICE": ["11,000원"], "PRICE_ONSITE": ["11,000원"], "PRICE_TYPE": ["현장판매"], "LINEUP": ["진화", "서지영", "오윤", "김명규"], "INSTAGRAM": ["@j__.lo.o2", "@blu_salt", "@woodangtang59", "@l1them"], "VENUE": [], "V_INSTA": [], "TICKET_OPEN_DATE": ["2025년 8월 16일"], "TICKET_OPEN_TIME": ["오후 3시"]}
{"text": "[#나첫콘] 티켓 오픈 안내 Men And Them : Believers ⠀ 한국 인디의 다음 페이지, 맨앤뎀의 ’나의 첫번째 콘서트‘ 🔔티켓오픈: 8.14(목) 7PM *멜론티켓 단독 오픈 ✅일시: 2025.09.07(일) 6PM ✅티켓가격: 33,000원 📍장소: KT&G 상상마당 라이브홀 (서울시 마포구 어울마당로 65, 지하 2층) ✅문의: 02-2014-2022 #상상마당 #상상마당음악지원사업 #음악지원사업 #2025나의첫번째콘서트 #나의첫번째콘서트 #나첫콘 #myfirstconcert #맨앤뎀 #MenAndThem @menandthem", "TITLE": ["Men And Them : Believers"], "DATE": ["8.14", "2025.09.07", "2025년 9월 7일 (일)"], "TIME": ["7pm", "6pm"], "PRICE": ["33,000원"], "PRICE_ONSITE": [], "PRICE_TYPE": [], "LINEUP": [], "INSTAGRAM": ["@menandthem"], "VENUE": ["KT", "상상마당"], "V_INSTA": [], "TICKET_OPEN_DATE": ["2025년 9월 7일 (일)"], "TICKET_OPEN_TIME": ["7pm"]}
{"text": "Night Of Victim Vol.64 The Worms @the__worms Garlixx @garlixx Purpura @band__purpura 우유강도 @wykd_official 2025. 8. 24.(일) Club VICTIM OPEN 18:00 START 18:30 25,000 KRW i 현매만 가능(계좌이체, 카드가능) ii 외부 음식 반입가능, 외부주류 반입금지 문의 DM or clubxvictim@gmail.com", "TITLE": ["Night Of Victim Vol", "64", "Worms"], "DATE": ["2025. 8. 24", "2025년 8월 24일"], "TIME": ["18:00", "18:30"], "PRICE": ["25,000원"], "PRICE_ONSITE": [], "PRICE_TYPE": ["현매만"], "LINEUP": ["The", "Garlixx", "Purpura", "우유강"], "INSTAGRAM": ["@the__worms", "@garlixx", "@band__purpura", "@wykd_official"], "VENUE": ["Club", "VICTIM"], "V_INSTA": [], "TICKET_OPEN_DATE": [], "TICKET_OPEN_TIME": []}
{"text": "EBS 스페이스 공감 한국 인디음악 30주년 특별 공연 We are Pioneers EBS 스페이스 공감과 세 팀의 파이오니어가 선사하는 특별한 무대! 우리 대중음악의 과거-현재-미래를 잇는 뜻깊은 공연이 펼쳐 집니다 [LINE-UP] Pioneer 01| 산만한시선 일상의 감성과 솔직함을 담은 포크 듀오! 앞으로의 행보가 더욱 기대되는 라이징 아티스트 @sanmanhan.official Pioneer 02 | 이날치 전 세계를 사로잡은 독보적 사운드! 한국 대중음악의 경계를 넓혀온 얼터너티브 팝 밴드 @leenalchi Pioneer 03| 김창완밴드 명실상부 록의 전설! 세대를 아우르는 음악으로 여전히 ’현재진행형‘ 레전드 @kimchangwanband [공연 정보] ✓ 일시: 2025. 09. 07(일) 6PM ✓ 장소: 노들섬 잔디마당 (서울특별시 용산구 양녕로 445) ✓ 관람 방법: 티켓 사전 예매 (무료) ✓ 티켓 예매 일정: 2025. 08. 18(월) 10AM 오픈 예정 ✓ 티켓 예매처: 노들섬 공식 홈페이지 * 티켓 예매와 관련한 자세한 사항은 추후 노들섬 공식 홈페이지 (nodeul.org)에서 확인하실 수 있습니다.", "TITLE": ["EBS 스페이스 공감", "주년 특별", "We are Pioneers EBS"], "DATE": ["2025. 09. 07", "2025. 08. 18", "2025년 9월 7일 (일)", "2025년 8월 18일 (월)"], "TIME": ["6pm", "10am"], "PRICE": ["2,025원"], "PRICE_ONSITE": [], "PRICE_TYPE": ["사전"], "LINEUP": ["노들섬"], "INSTAGRAM": ["@sanmanhan.official", "@leenalchi", "@kimchangwanband"], "VENUE": ["잔디마당"], "V_INSTA": [], "TICKET_OPEN_DATE": ["2025년 8월 18일 (월)"], "TICKET_OPEN_TIME": ["10am"]}
{"text": "[톰밴드 30주년 전국제패 콘서트-거제 공지] 생각보다 괜찮은 밴드(?) 빅재미 보장 ‘톰밴드’ 의 서른살을 함께 축하해요🎉 🗓️ 일시 : 2025년 8월 16일 토요일 오후 7시 📍 장소 : 경남 거제시 언드(UND) - 경남 거제시 거제대로 3734 지하1층 언드 🎫 입장료 : 예매 20,000원, 현매 25,000원 - 프로필 링크 클릭 후, 해당 공연의 예매폼 작성 및 입장료 송금 끝! - 입금 계좌 : 카카오뱅크 3333-27-7638678 (김용준) 👥 라인업 톰밴드 @tomband_official 레드클라인 @redcline__ 인문계 @band_inmungae 고고482 @band_gogo482 (Guest) #톰밴드30주년 #전국재패 #투어공연 #언드 #락밴드 #생각이상으로괜찮은밴드 #재미보장 #열정 #톰밴드 #레드클라인 #인문계 #고고482 #빅재미", "TITLE": ["톰밴드", "주년 전국제패 콘서트 - 거제"], "DATE": ["2025년 8월 16일"], "TIME": ["오후 7시"], "PRICE": ["20,000원", "25,000원", "7,638,678원"], "PRICE_ONSITE": ["25,000원"], "PRICE_TYPE": ["예매", "현매"], "LINEUP": ["톰밴드", "레드클라인", "인문계", "의 서른살", "축하해요"], "INSTAGRAM": ["@tomband_official", "@redcline__", "@band_inmungae", "@band_gogo482"], "VENUE": ["언드"], "V_INSTA": [], "TICKET_OPEN_DATE": [], "TICKET_OPEN_TIME": []}
{"text": "[#공연안내] 김세현과 좋은 친구들 Live Concert ✅ 공연일시: 2025.08.16(토) 6PM ✅ 예매처: 전화 문의 ✅ 티켓가격: 현장 80,000원 / 예매 70,000원 📍공연장소: KT&G 상상마당 라이브홀 (서울시 마포구 어울마당로 65) ✅ 문의: 김세현과 좋은 친구들 010-4173-6735 #상상마당 #상상마당라이브홀", "TITLE": ["김세현과 좋은 친구들 Live Concert"], "DATE": ["2025.08.16", "2025년 8월 16일 (토)"], "TIME": ["6pm"], "PRICE": ["80,000원", "70,000원"], "PRICE_ONSITE": ["80,000원"], "PRICE_TYPE": ["현매", "예매"], "LINEUP": [], "INSTAGRAM": [], "VENUE": ["KT", "상상마당"], "V_INSTA": [], "TICKET_OPEN_DATE": [], "TICKET_OPEN_TIME": []}
{"text": "#2025라라라온 #LaLaLaON 📅 8월 20일(수) 오후 8시 📍 언플러그드 홍대 @cafeunplugged (서울특별시 마포구 와우산로 33길 26, 지하 1층) 🥁 𝗚𝗘𝗡𝗥𝗘 포크 / 일렉트로닉 🎤 𝗟𝗜𝗡𝗘 𝗨𝗣 소각소각 @sogak_sogak 윤새 @yunsaemusic 시와 @withsiwa ──────────────────── 𝟐𝟎𝟐𝟓 𝑳𝒂𝑳𝒂𝑳𝒂𝑶𝑵 🍃 공연 개요 - 기간 : 8월 16일(토) ~ 11월 14일(금) - 장소 : 전국 소규모 공연장 53곳 🍃 예매 안내 - 예매처 : 멜론티켓 단독 판매 - 티켓오픈 : 8월 6일(수) 오후 2시, 1차 티켓오픈 - 가격 : 전석 22,000원 🍃문의 - 인스타그램 : @lalalaon_official DM", "TITLE": ["#LaLaLaON"], "DATE": ["8월 20일 (수)", "8월 16일", "11월 14일", "8월 6일", "8월 16일 (토)", "11월 14일 (금)", "8월 6일 (수)"], "TIME": ["오후 8시", "오후 2시"], "PRICE": ["22,000원"], "PRICE_ONSITE": [], "PRICE_TYPE": [], "LINEUP": ["소각소각", "윤새"], "INSTAGRAM": ["@cafeunplugged", "@sogak_sogak", "@yunsaemusic", "@withsiwa"], "VENUE": ["홍대"], "V_INSTA": [], "TICKET_OPEN_DATE": ["8월 6일 (수)"], "TICKET_OPEN_TIME": ["오후 2시"]}
{"text": "스트레인지프룻 20주년공연 서른네번째는 일본 Japonicus 레이블과 협업으로 진행합니다. 이미 여러차례 방한해서 멋진 공연을 보여준바 있는 Ray? Oh…Needa!!, 올해 후지락 페스티벌등 전세계 페스티벌에 초대받는 DJ Txako, 그리고 이번에 처음으로 소개되는 Yowamushi club 이 참가하고 한국팀으로는 Low high low가 같이 합니다. 멋진밤이 되리라 생각합니다. 일시: 2025. 8. 28.(목) 저녁 8시 장소: 스트레인지 프룻 입장료: 3만원 현매로 진행됩니다. Artist information ✅ Ray? Oh... Needa!! (Japan) 도쿄 시부야를 기반으로 활동하는 5인조 밴드 **Ray? Oh... Needa!!**는 보컬/기타 Takeshi Oe와 기타/코러스 Masahito Shibata를 중심으로, 70년대 록의 거친 질감과 현대적인 감각을 넘나드는 사운드를 선보입니다. Fishbone의 Angelo Moore, Capsula(스페인), Lowdown 30(한국), Willis Drummond(프랑스) 등 다양한 해외 아티스트와의 협업을 통해 국제적인 입지를 다져왔습니다. 2022년 EP AGOG와 BRIO를 발표하며 얼터너티브, 펑크, 덥, 일렉트로, 인더스트리얼을 넘나드는 다채로운 음악 세계를 본격화했고, 2023년에는 스페인, 바스크, 중국, 프랑스 투어를 성공적으로 마쳤습니다. 이제 곧, 한국에서의 세 번째 투어가 시작됩니다. ✅ DJ Txako (Japan) @txakojaponicus 아시아 최초의 글로벌 & 메스티소 비트 여성 DJ, 전설적인 DJ 콜렉티브 Caribbean Dandy의 핵심 멤버 DJ Txako는 유쾌하고 에너지 넘치는 무대로 아시아와 유럽 전역의 페스티벌을 누비고 있는 DJ입니다. 올해 후지 록 페스티벌에 13년 연속 출연을 비롯해 스페인, 멕시코, 이탈리아, 프랑스, 몽골, 대만, 한국 등 전 세계 주요 월드뮤직 페스티벌에서 관객과 호흡해왔습니다. 또한 Flogging Molly, Fishbone, Manu Chao, Gaz Mayall, Tiken Jah Fakoly, 등 다양한 세계적인 아티스트들과 협업하고 투어하며, 15,000명 이상을 앞에 둔 무대에서도 폭발적인 에너지를 선사해왔습니다. 아시아와 유럽의 DJ 씬에 지대한 영향을 끼쳐온 그녀. 지금 볼륨을 올리고, DJ Txako의 전방위 사운드를 맞이할 준비를 하세요! ✅ Yowamushi Club (Japan) “약하지만, 그래서 더 강하다.” 리더 유스케 야수지마(Yusuke Yasujima)를 중심으로, 2017년 2월, ‘약함 속의 힘’을 찾기 위해 결성된 밴드 Weak but Strong. 이들은 일본 전역의 다양한 뮤지션들과 협업하며 끊임없이 진화해왔고, 4인의 핵심 멤버는 얼터너티브, 펑크, 뉴웨이브, 일렉트로니카, 힙합을 아날로그 전자음향 위에 뒤섞어, 자신들만의 독특한 사운드를 완성해냈습니다. 그들의 음악은 끝없이 이어지는 록앤롤의 여정을 이야기합니다. 작고 약한 존재들이 모여 만들어낸 가장 강력한 사운드. 약함을 무기로 삼는 새로운 록의 선언! Low high low 로우하이로우는 낮음과 높음이라는 뜻을 가지고 있다. ‘만들어지고 들려지고 해체한다’는 의미를 내포한 이름으로 이스턴 사이드킥의 리더였던 고한결과 우주아가씨 보컬이었던 윤택선 주축으로 2019년 결성되었다. 아시안 체어샷의 황영원, 데카당의 드럼 이현석이 합류하여 지금의 멤버가 완성되었다. 목소리와 실체의 악기만으로, 손에 잡힐 듯 실현 가능한 사운드만을 추구한다. 상실의 이미지를 게러지 록이라는 수단을 통해 나타낸다. 포스터디자인 @pinessong", "TITLE": [], "DATE": ["2025. 8. 28", "2025년 8월 28일"], "TIME": ["저녁 8시"], "PRICE": [], "PRICE_ONSITE": [], "PRICE_TYPE": ["현매로"], "LINEUP": ["스트레인지프룻"], "INSTAGRAM": [], "VENUE": ["후지락", "스트레인지", "전세계 페스티벌", "록 페스티벌", "월드뮤직 페스티벌"], "V_INSTA": [], "TICKET_OPEN_DATE": [], "TICKET_OPEN_TIME": []}
{"text": "배인혁 [열두달] 🔸일시 : 2025년 8월 14일(목) 8PM 🔸장소 : 살롱문보우 (서울 마포구 잔다리로 113, B1) #살롱문보우 #salonmoonbow #문보우 #망원 #합정 #홍대 #공연 #공연장 #대관 #공연대관 #장소대관 #모임대관 #인터뷰대관 #촬영스튜디오대관 #배인혁 #열두달 #로맨틱펀치", "TITLE": ["배인혁", "열두달"], "DATE": ["2025년 8월 14일", "2025년 8월 14일 (목)"], "TIME": ["8pm"], "PRICE": [], "PRICE_ONSITE": [], "PRICE_TYPE": [], "LINEUP": [], "INSTAGRAM": [], "VENUE": [], "V_INSTA": [], "TICKET_OPEN_DATE": [], "TICKET_OPEN_TIME": []}
{"text": "첫, 사랑을 위하여 OST Part 1 최정은(izna)의 'Lover'이 발매되었습니다. 청량하고 파워풀한 음색으로 사랑받는 그룹 izna(이즈나)의 보컬 최정은이 데뷔 후 처음으로 선보이는 드라마 OST입니다. 드라마의 감정선을 쌓아 올리는 첫 번째 OST ‘Lover’는 사랑을 가장 순수한 시선으로 담아낸 곡입니다. 가사 속 반복되는 “Lover”는 나의 첫사랑이자 딸을 부르는 말로, 사랑의 시작과 완성, 그리고 과거와 미래를 잇는 깊은 감정을 표현하고 있습니다. #첫사랑을위하여 #최정은 #이즈나 #Lover #톤스튜디오 #TONESTUDIO Mixed & Mastered by 최민성 @ TONE Studio Seoul", "TITLE": ["사랑을", "OST Part 1"], "DATE": [], "TIME": [], "PRICE": [], "PRICE_ONSITE": [], "PRICE_TYPE": [], "LINEUP": [], "INSTAGRAM": [], "VENUE": [], "V_INSTA": [], "TICKET_OPEN_DATE": [], "TICKET_OPEN_TIME": []}
{"text": "[#나첫콘] 티켓 오픈 안내 권그린 단독 공연 <GREENY : Forest of our own> ⠀ 우린 같지 않지만, 같은 숲을 만들 수 있어 🔔티켓오픈: 8.14(목) 7PM *멜론티켓 단독 오픈 ✅일시: 2025.09.06(토) 8PM ✅티켓가격: 38,000원 📍장소: KT&G 상상마당 라이브홀 (서울시 마포구 어울마당로 65, 지하 2층) ✅문의: 02-2014-2022 #상상마당 #상상마당음악지원사업 #음악지원사업 #2025나의첫번째콘서트 #나의첫번째콘서트 #나첫콘 #myfirstconcert #권그린 #GREENY @iam_green__", "TITLE": ["권그린 단독 공연", "GREENY : Forest of our own"], "DATE": ["8.14 (목)", "2025.09.06", "2025년 9월 6일 (토)"], "TIME": ["7pm", "8pm"], "PRICE": ["38,000원"], "PRICE_ONSITE": [], "PRICE_TYPE": [], "LINEUP": [], "INSTAGRAM": ["@iam_green__"], "VENUE": ["KT", "상상마당"], "V_INSTA": [], "TICKET_OPEN_DATE": ["2025년 9월 6일 (토)"], "TICKET_OPEN_TIME": ["7pm"]}
{"text": "Night Of Victim Vol.63 The Redemptions @band_the_redemptions Nimbus @nimbus_grunge Guny N Guns @guny_n_guns Varnish @varnish_band 2025. 8. 17.(일) Club VICTIM OPEN 18:00 START 18:30 25,000 KRW i 현매만 가능(계좌이체, 카드가능) ii 외부 음식 반입가능, 외부주류 반입금지 문의 DM or clubxvictim@gmail.com Special Thanx to @coszise", "TITLE": ["Night Of Victim Vol", "63"], "DATE": ["2025. 8. 17", "2025년 8월 17일"], "TIME": ["18:00", "18:30"], "PRICE": ["25,000원"], "PRICE_ONSITE": [], "PRICE_TYPE": ["현매만"], "LINEUP": ["The Redemptions", "Nimbus", "N Guns", "Varnish"], "INSTAGRAM": ["@band_the_redemptions", "@nimbus_grunge", "@guny_n_guns", "@varnish_band"], "VENUE": ["Club"], "V_INSTA": [], "TICKET_OPEN_DATE": [], "TICKET_OPEN_TIME": []}
